{
  "openapi": "3.0.1",
  "info": {
    "title": "EmailCodeVerificationAPI",
    "version": "1.0"
  },
  "paths": {
    "/api/Verification/generate": {
      "post": {
        "tags": [
          "Verification"
        ],
        "requestBody": {
          "content": {
            "application/json": {
              "schema": {
                "$ref": "#/components/schemas/EmailRequest"
              }
            },
            "text/json": {
              "schema": {
                "$ref": "#/components/schemas/EmailRequest"
              }
            },
            "application/*+json": {
              "schema": {
                "$ref": "#/components/schemas/EmailRequest"
              }
            }
          }
        },
        "responses": {
          "200": {
            "description": "OK"
          }
        }
      }
    },
    "/api/Verification/validate": {
      "post": {
        "tags": [
          "Verification"
        ],
        "requestBody": {
          "content": {
            "application/json": {
              "schema": {
                "$ref": "#/components/schemas/CodeValidationRequest"
              }
            },
            "text/json": {
              "schema": {
                "$ref": "#/components/schemas/CodeValidationRequest"
              }
            },
            "application/*+json": {
              "schema": {
                "$ref": "#/components/schemas/CodeValidationRequest"
              }
            }
          }
        },
        "responses": {
          "200": {
            "description": "OK"
          }
        }
      }
    }
  },
  "components": {
    "schemas": {
      "CodeValidationRequest": {
        "type": "object",
        "properties": {
          "code": {
            "type": "string",
            "nullable": true
          }
        },
        "additionalProperties": false
      },
      "EmailRequest": {
        "type": "object",
        "properties": {
          "toEmail": {
            "type": "string",
            "nullable": true
          }
        },
        "additionalProperties": false
      }
    }
  }
}